single_instance_model
